components/__init__.py
components/base.py
components/btn_delete.py
components/btn_flex.py
components/date.py
components/state.py
components/styles.py
components/sub_task.py
components/text_area.py
components/title.py
flet_components-0.0.9.dist-info/LICENSE
flet_components-0.0.9.dist-info/METADATA
flet_components-0.0.9.dist-info/WHEEL
flet_components-0.0.9.dist-info/top_level.txt
flet_components-0.0.9.dist-info/RECORD
