Metadata-Version: 2.2
Name: flet_components
Version: 0.0.9
Summary: Conjunto de componentes personalizados para Flet
Author-email: Ruben Chavez <juanrubenc78@gmail.com>
License: MIT License
Project-URL: Homepage, https://github.com/Duz-Dev/flet_component
Project-URL: Download, https://github.com/Duz-Dev/flet_component/tarball/0.0.9
Project-URL: Documentation, https://github.com/Duz-Dev/flet_component/wiki
Keywords: flet,components,UI,Python
Classifier: Development Status :: 3 - Alpha
Classifier: Intended Audience :: Developers
Classifier: Topic :: Software Development :: Libraries
Classifier: Programming Language :: Python :: 3
Classifier: License :: OSI Approved :: MIT License
Classifier: Operating System :: OS Independent
Requires-Python: >=3.12
License-File: LICENSE
Requires-Dist: flet>=0.25.2
